usbcan/ECanVci64.dll
usbcan/__init__.py
usbcan/somebus.py
usbcan-0.0.4.dist-info/LICENSE
usbcan-0.0.4.dist-info/METADATA
usbcan-0.0.4.dist-info/WHEEL
usbcan-0.0.4.dist-info/top_level.txt
usbcan-0.0.4.dist-info/RECORD
