Metadata-Version: 2.1
Name: usbcan
Version: 0.0.4
Summary: USBCAN driver package
Home-page: https://github.com/laigui/usbcan
Author: Laigui Qin
Author-email: laigui@gmail.com
License: MIT
Platform: UNKNOWN
Classifier: Development Status :: 2 - Pre-Alpha
Classifier: License :: OSI Approved :: MIT License
Classifier: Programming Language :: Python :: 3.7
